{
    "stocks": {
        "^TWII": {
            "Price": 46255.26,
            "Currency": "PTS"
        },
        "^GSPC": {
            "Price": 7358.22,
            "Currency": "PTS"
        },
        "^IXIC": {
            "Price": 25476.64,
            "Currency": "PTS"
        },
        "^DJI": {
            "Price": 51848.9,
            "Currency": "PTS"
        },
        "^SOX": {
            "Price": 13458.2,
            "Currency": "PTS"
        },
        "2454": {
            "Price": 4310.0,
            "Currency": "TWD"
        },
        "6257": {
            "Price": 238.0,
            "Currency": "TWD"
        },
        "2882": {
            "Price": 111.5,
            "Currency": "TWD"
        },
        "2887": {
            "Price": 31.85,
            "Currency": "TWD"
        },
        "2884": {
            "Price": 35.45,
            "Currency": "TWD"
        },
        "2890": {
            "Price": 39.95,
            "Currency": "TWD"
        },
        "00878": {
            "Price": 33.75,
            "Currency": "TWD"
        },
        "00713": {
            "Price": 60.85,
            "Currency": "TWD"
        },
        "006208": {
            "Price": 248.1,
            "Currency": "TWD"
        },
        "SPY": {
            "Price": 733.24,
            "Currency": "USD"
        },
        "VT": {
            "Price": 154.26,
            "Currency": "USD"
        },
        "GRAB": {
            "Price": 3.49,
            "Currency": "USD"
        },
        "AVGO": {
            "Price": 382.07,
            "Currency": "USD"
        },
        "GOOGL": {
            "Price": 345.29,
            "Currency": "USD"
        },
        "NVDA": {
            "Price": 199.0,
            "Currency": "USD"
        },
        "CRWD": {
            "Price": 673.02,
            "Currency": "USD"
        },
        "PLTR": {
            "Price": 113.5,
            "Currency": "USD"
        },
        "RBRK": {
            "Price": 74.52,
            "Currency": "USD"
        }
    },
    "institutional_investors": {
        "自營商(自行買賣)": "-22.54 億",
        "自營商(避險)": "-47.47 億",
        "投信": "161.41 億",
        "外資及陸資(不含外資自營商)": "-405.1 億",
        "外資自營商": "0.0 億",
        "合計": "-313.7 億"
    },
    "metadata": {
        "UpdateTime": "2026-06-25 10:24:08"
    }
}