{
    "stocks": {
        "^TWII": {
            "Price": 39521.73,
            "Currency": "PTS"
        },
        "^GSPC": {
            "Price": 7138.8,
            "Currency": "PTS"
        },
        "^IXIC": {
            "Price": 24663.8,
            "Currency": "PTS"
        },
        "^DJI": {
            "Price": 49141.93,
            "Currency": "PTS"
        },
        "^SOX": {
            "Price": 10035.58,
            "Currency": "PTS"
        },
        "2454": {
            "Price": 2615.0,
            "Currency": "TWD"
        },
        "6257": {
            "Price": 180.5,
            "Currency": "TWD"
        },
        "2882": {
            "Price": 74.7,
            "Currency": "TWD"
        },
        "2887": {
            "Price": 24.4,
            "Currency": "TWD"
        },
        "2884": {
            "Price": 32.45,
            "Currency": "TWD"
        },
        "2890": {
            "Price": 31.9,
            "Currency": "TWD"
        },
        "00878": {
            "Price": 25.3,
            "Currency": "TWD"
        },
        "00713": {
            "Price": 53.0,
            "Currency": "TWD"
        },
        "006208": {
            "Price": 213.15,
            "Currency": "TWD"
        },
        "SPY": {
            "Price": 711.69,
            "Currency": "USD"
        },
        "VT": {
            "Price": 149.46,
            "Currency": "USD"
        },
        "GRAB": {
            "Price": 3.86,
            "Currency": "USD"
        },
        "AVGO": {
            "Price": 399.83,
            "Currency": "USD"
        },
        "GOOGL": {
            "Price": 349.78,
            "Currency": "USD"
        },
        "NVDA": {
            "Price": 213.17,
            "Currency": "USD"
        },
        "CRWD": {
            "Price": 454.99,
            "Currency": "USD"
        },
        "PLTR": {
            "Price": 141.18,
            "Currency": "USD"
        },
        "RBRK": {
            "Price": 54.58,
            "Currency": "USD"
        }
    },
    "institutional_investors": {
        "自營商(自行買賣)": "-9.05 億",
        "自營商(避險)": "12.57 億",
        "投信": "56.42 億",
        "外資及陸資(不含外資自營商)": "-392.98 億",
        "外資自營商": "0.0 億",
        "合計": "-333.05 億"
    },
    "metadata": {
        "UpdateTime": "2026-04-28 23:52:50"
    }
}